adafruit_circuitpython_esp32s2tft-2.0.4.dist-info/licenses/LICENSE
adafruit_esp32s2tft/__init__.py
adafruit_esp32s2tft/graphics.py
adafruit_esp32s2tft/network.py
adafruit_esp32s2tft/peripherals.py
adafruit_circuitpython_esp32s2tft-2.0.4.dist-info/METADATA
adafruit_circuitpython_esp32s2tft-2.0.4.dist-info/WHEEL
adafruit_circuitpython_esp32s2tft-2.0.4.dist-info/top_level.txt
adafruit_circuitpython_esp32s2tft-2.0.4.dist-info/RECORD
