Metadata-Version: 2.4
Name: adafruit-circuitpython-esp32s2tft
Version: 2.0.4
Summary: Helper library for the Adafruit ESP32-S2 TFT Feather
Author-email: Adafruit Industries <circuitpython@adafruit.com>
License: MIT
Project-URL: Homepage, https://github.com/adafruit/Adafruit_CircuitPython_ESP32S2TFT
Keywords: adafruit,esp32,esp32s2,tft,espressif,feather,hardwaremicropython,circuitpython
Classifier: Intended Audience :: Developers
Classifier: Topic :: Software Development :: Libraries
Classifier: Topic :: Software Development :: Embedded Systems
Classifier: Topic :: System :: Hardware
Classifier: License :: OSI Approved :: MIT License
Classifier: Programming Language :: Python :: 3
License-File: LICENSE
Requires-Dist: Adafruit-Blinka-displayio
Requires-Dist: Adafruit-Blinka
Requires-Dist: adafruit-circuitpython-minimqtt
Requires-Dist: adafruit-circuitpython-requests
Requires-Dist: adafruit-circuitpython-neopixel
Requires-Dist: adafruit-circuitpython-portalbase
Provides-Extra: optional
Dynamic: license-file
